k_silhouette-0.1.4.dist-info/licenses/LICENSE
ksil/__init__.py
ksil/ksil.py
k_silhouette-0.1.4.dist-info/METADATA
k_silhouette-0.1.4.dist-info/WHEEL
k_silhouette-0.1.4.dist-info/top_level.txt
k_silhouette-0.1.4.dist-info/RECORD
