Metadata-Version: 2.4
Name: k_silhouette
Version: 0.1.4
Summary: K-Sil Clustering: A silhouette-guided instance-weighted k-means algorithm that integrates silhouette scores into the clustering process to improve clustering quality.
Home-page: https://github.com/semoglou/ksil
Author: Aggelos Semoglou
Author-email: a.semoglou@outlook.com
License: MIT
Requires-Python: >=3.8
License-File: LICENSE
Requires-Dist: numpy
Requires-Dist: pandas
Requires-Dist: scikit-learn
Requires-Dist: scipy
Requires-Dist: joblib>=1.4.2
Dynamic: author
Dynamic: author-email
Dynamic: description
Dynamic: description-content-type
Dynamic: home-page
Dynamic: license
Dynamic: license-file
Dynamic: requires-dist
Dynamic: requires-python
Dynamic: summary
